airbrake/__init__.py
airbrake/handlers.py
django_airbrake-1.3.0.dist-info/METADATA
django_airbrake-1.3.0.dist-info/RECORD
django_airbrake-1.3.0.dist-info/WHEEL
django_airbrake-1.3.0.dist-info/top_level.txt
