Metadata-Version: 2.1
Name: django-airbrake
Version: 1.3.0
Summary: Airbrake exception logger for Django
Home-page: http://github.com/Bouke/django-airbrake
Author: Bouke Haarsma
Author-email: bouke@haarsma.eu
License: MIT
Platform: UNKNOWN
Classifier: Development Status :: 5 - Production/Stable
Classifier: Environment :: Web Environment
Classifier: Framework :: Django
Classifier: Intended Audience :: Developers
Classifier: License :: OSI Approved :: MIT License
Classifier: Operating System :: OS Independent
Classifier: Programming Language :: Python
Classifier: Programming Language :: Python :: 2
Classifier: Programming Language :: Python :: 2.7
Classifier: Programming Language :: Python :: 3
Classifier: Programming Language :: Python :: 3.4
Classifier: Programming Language :: Python :: 3.5
Classifier: Programming Language :: Python :: 3.6
Classifier: Topic :: System :: Logging
Requires-Dist: Django (>=1.11)
